tiktokbacot/__init__.py
tiktokbacot/tts.py
tiktokbacot-1.0.1.dist-info/METADATA
tiktokbacot-1.0.1.dist-info/WHEEL
tiktokbacot-1.0.1.dist-info/top_level.txt
tiktokbacot-1.0.1.dist-info/RECORD
