Metadata-Version: 2.1
Name: tiktokbacot
Version: 1.0.1
Summary: Paket untuk mengubah teks menjadi suara dengan API TikTok
Home-page: https://github.com/tigrilminnada/tiktokbacot
Author: masanto
Author-email: seller.digitalocean@gmail.com
License: MIT
Platform: UNKNOWN
Classifier: Development Status :: 3 - Alpha
Classifier: Intended Audience :: Developers
Classifier: License :: OSI Approved :: MIT License
Classifier: Programming Language :: Python :: 3
Classifier: Programming Language :: Python :: 3.6
Classifier: Programming Language :: Python :: 3.7
Classifier: Programming Language :: Python :: 3.8
Classifier: Programming Language :: Python :: 3.9
Requires-Dist: requests
